SLUSpell-0.2.0.data/scripts/setup
sluspell/__init__.py
sluspell/main.py
sluspell/apps/__init__.py
sluspell/apps/langSpec.py
sluspell/apps/spellchecker.py
sluspell/apps/assets/dict/en_bi_dict.pkl
sluspell/apps/assets/dict/en_chars.pkl
sluspell/apps/assets/dict/en_dict.pkl
sluspell/apps/assets/dict/ga_bi_dict.pkl
sluspell/apps/assets/dict/ga_chars.pkl
sluspell/apps/assets/dict/ga_dict.pkl
sluspell/apps/assets/dict/ga_dict_uni.pkl
sluspell/static/css/style.css
sluspell/static/img/favicon.png
sluspell/static/img/ie.svg
sluspell/static/img/us.svg
sluspell/static/js/async.js
sluspell/static/js/bootstrap.min.js
sluspell/static/js/main.js
sluspell/static/js/popper.js
sluspell/static/js/script.js
sluspell/templates/index.html
sluspell/templates/assets/main_page.pkl
sluspell/templates/auth/login.html
sluspell/templates/auth/register.html
SLUSpell-0.2.0.dist-info/LICENSE.txt
SLUSpell-0.2.0.dist-info/METADATA
SLUSpell-0.2.0.dist-info/WHEEL
SLUSpell-0.2.0.dist-info/entry_points.txt
SLUSpell-0.2.0.dist-info/top_level.txt
SLUSpell-0.2.0.dist-info/RECORD
