Metadata-Version: 2.1
Name: SLUSpell
Version: 0.2.0
Summary: SLUSpell is an open-source spell checker that uses multiple techniques to find misspelled words.
Home-page: https://github.com/mahdirahbar/SLUSpell
Author: Mahdi Rahbar
Author-email: mahdirahbar01@gmail.com
License: UNKNOWN
Platform: UNKNOWN
Classifier: Programming Language :: Python :: 3
Classifier: License :: OSI Approved :: GNU General Public License v3 (GPLv3)
Classifier: Operating System :: OS Independent
License-File: LICENSE.txt
Requires-Dist: flask
Requires-Dist: numpy
